certbot_gitlab/__init__.py
certbot_gitlab/configurator.py
certbot_gitlab-0.1.0.dist-info/METADATA
certbot_gitlab-0.1.0.dist-info/RECORD
certbot_gitlab-0.1.0.dist-info/WHEEL
certbot_gitlab-0.1.0.dist-info/entry_points.txt
certbot_gitlab-0.1.0.dist-info/top_level.txt
