Metadata-Version: 2.1
Name: certbot-gitlab
Version: 0.1.0
Summary: GitLab Pages plugin for Certbot
Home-page: https://gitlab.com/sommd/certbot-gitlab
Author: sommd
License: Apache Licence 2.0
Platform: UNKNOWN
Requires-Dist: certbot
Requires-Dist: zope.interface
Requires-Dist: python-gitlab
